mcmqtt/__init__.py
mcmqtt/main.py
mcmqtt/broker/__init__.py
mcmqtt/broker/manager.py
mcmqtt/cli/__init__.py
mcmqtt/cli/parser.py
mcmqtt/cli/version.py
mcmqtt/config/__init__.py
mcmqtt/config/env_config.py
mcmqtt/logging/__init__.py
mcmqtt/logging/setup.py
mcmqtt/mcp/__init__.py
mcmqtt/mcp/server.py
mcmqtt/middleware/__init__.py
mcmqtt/middleware/broker_middleware.py
mcmqtt/mqtt/__init__.py
mcmqtt/mqtt/client.py
mcmqtt/mqtt/connection.py
mcmqtt/mqtt/publisher.py
mcmqtt/mqtt/subscriber.py
mcmqtt/mqtt/types.py
mcmqtt/server/__init__.py
mcmqtt/server/runners.py
mcmqtt-2025.9.17.1.dist-info/METADATA
mcmqtt-2025.9.17.1.dist-info/WHEEL
mcmqtt-2025.9.17.1.dist-info/entry_points.txt
mcmqtt-2025.9.17.1.dist-info/licenses/LICENSE
mcmqtt-2025.9.17.1.dist-info/RECORD
