Metadata-Version: 2.4
Name: mcmqtt
Version: 2025.9.17.1
Summary: FastMCP MQTT Server - Enabling MQTT integration for MCP clients
Project-URL: Homepage, https://git.supported.systems/MCP/mcmqtt
Project-URL: Repository, https://git.supported.systems/MCP/mcmqtt.git
Project-URL: Issues, https://git.supported.systems/MCP/mcmqtt/issues
Project-URL: Documentation, https://git.supported.systems/MCP/mcmqtt/src/branch/main/README.md
Author-email: Ryan Malloy <ryan@malloys.us>
License: MIT
License-File: LICENSE
Requires-Python: >=3.11
Requires-Dist: amqtt>=0.11.2
Requires-Dist: asyncio-mqtt>=0.16.0
Requires-Dist: fastmcp>=0.1.0
Requires-Dist: paho-mqtt>=2.1.0
Requires-Dist: pydantic>=2.10.0
Requires-Dist: pytest-cov>=7.0.0
Requires-Dist: rich>=13.9.0
Requires-Dist: structlog>=24.4.0
Requires-Dist: typer>=0.15.0
Requires-Dist: uvloop>=0.21.0
Provides-Extra: dev
Requires-Dist: black>=24.10.0; extra == 'dev'
Requires-Dist: mypy>=1.13.0; extra == 'dev'
Requires-Dist: pre-commit>=4.0.0; extra == 'dev'
Requires-Dist: pytest-asyncio>=0.24.0; extra == 'dev'
Requires-Dist: pytest-cov>=6.0.0; extra == 'dev'
Requires-Dist: pytest>=8.3.0; extra == 'dev'
Requires-Dist: ruff>=0.8.0; extra == 'dev'
